seaborn_analyzer/__init__.py
seaborn_analyzer/_cv_eval_set.py
seaborn_analyzer/_cv_eval_set_old.py
seaborn_analyzer/custom_class_plot.py
seaborn_analyzer/custom_hist_plot.py
seaborn_analyzer/custom_pair_plot.py
seaborn_analyzer/custom_reg_plot.py
seaborn_analyzer/multiclass_fitparams.py
seaborn_analyzer-0.3.6.dist-info/LICENSE
seaborn_analyzer-0.3.6.dist-info/METADATA
seaborn_analyzer-0.3.6.dist-info/WHEEL
seaborn_analyzer-0.3.6.dist-info/top_level.txt
seaborn_analyzer-0.3.6.dist-info/RECORD
