Metadata-Version: 2.1
Name: seaborn-analyzer
Version: 0.3.6
Summary: seaborn-analyzer: data visualization of regression, classification and distribution
Home-page: https://github.com/c60evaporator/seaborn-analyzer
Download-URL: https://github.com/c60evaporator/seaborn-analyzer
Author: Kenta Nakamura
Author-email: c60evaporator@gmail.com
Maintainer: Kenta Nakamura
Maintainer-email: c60evaporator@gmail.com
License: BSD 3-Clause
Classifier: Intended Audience :: Science/Research
Classifier: License :: OSI Approved :: BSD License
Classifier: Programming Language :: Python :: 3
Classifier: Programming Language :: Python :: 3.6
Classifier: Programming Language :: Python :: 3.7
Classifier: Programming Language :: Python :: 3.8
Classifier: Programming Language :: Python :: 3.9
Classifier: Programming Language :: Python :: 3 :: Only
Classifier: Topic :: Scientific/Engineering
Classifier: Topic :: Scientific/Engineering :: Visualization
Classifier: Topic :: Scientific/Engineering :: Artificial Intelligence
Classifier: Topic :: Multimedia :: Graphics
Classifier: Framework :: Matplotlib
Requires-Python: >=3.6
License-File: LICENSE
Requires-Dist: matplotlib >=3.7.1
Requires-Dist: seaborn >=0.12.2
Requires-Dist: numpy >=1.22.1
Requires-Dist: pandas >=2.0.2
Requires-Dist: scipy >=1.10.1
Requires-Dist: scikit-learn >=1.2.2
Requires-Dist: lightgbm >=3.3.5
Provides-Extra: tutorial
Requires-Dist: mlxtend >=0.18.0 ; extra == 'tutorial'
Requires-Dist: xgboost >=1.7.4 ; extra == 'tutorial'
